discoverySimulator/Component.py
discoverySimulator/Frame.py
discoverySimulator/Object.py
discoverySimulator/Observable.py
discoverySimulator/Pose.py
discoverySimulator/ZoomController.py
discoverySimulator/__init__.py
discoverySimulator/config.py
discoverySimulator/actuators/Actuator.py
discoverySimulator/actuators/LED.py
discoverySimulator/actuators/Wheel.py
discoverySimulator/actuators/__init__.py
discoverySimulator/examples/__init__.py
discoverySimulator/examples/blink.py
discoverySimulator/examples/blinkWithoutSleep.py
discoverySimulator/examples/fuzzyLogicObstacleAvoidance.py
discoverySimulator/examples/parkingScenario.py
discoverySimulator/examples/roadFollowing.py
discoverySimulator/examples/robotMovement.py
discoverySimulator/examples/simpleObstacleAvoidance.py
discoverySimulator/examples/useOfLIDAR.py
discoverySimulator/examples/useOfPathFinding.py
discoverySimulator/examples/useOfReinforcementLearning.py
discoverySimulator/examples/useOfTelemetersToMesureSpeed.py
discoverySimulator/interface/components/Button.py
discoverySimulator/interface/components/__init__.py
discoverySimulator/interface/views/About.py
discoverySimulator/interface/views/Explorer.py
discoverySimulator/interface/views/ExplorerInfo.py
discoverySimulator/interface/views/ExplorerToolbar.py
discoverySimulator/interface/views/ExplorerTree.py
discoverySimulator/interface/views/Footer.py
discoverySimulator/interface/views/Interface.py
discoverySimulator/interface/views/Scene.py
discoverySimulator/interface/views/SceneOverview.py
discoverySimulator/interface/views/Toolbar.py
discoverySimulator/interface/views/__init__.py
discoverySimulator/obstacles/CircularObstacle.py
discoverySimulator/obstacles/Obstacle.py
discoverySimulator/obstacles/RectangularObstacle.py
discoverySimulator/obstacles/__init__.py
discoverySimulator/representation/Representation.py
discoverySimulator/representation/__init__.py
discoverySimulator/representation/shapes/Border.py
discoverySimulator-1.0.0.dist-info/LICENSE
discoverySimulator-1.0.0.dist-info/METADATA
discoverySimulator-1.0.0.dist-info/WHEEL
discoverySimulator-1.0.0.dist-info/top_level.txt
discoverySimulator-1.0.0.dist-info/RECORD
