Metadata-Version: 2.1
Name: discoverySimulator
Version: 1.0.0
Summary: discoverySimulator is a Python package allowing to simulate environments in which mobile robots evolve. This simulator is accompanied by an interface allowing to visualize and control the simulation. This package is ideal for a playful learning of python and a discovery of mobile robotics.
Home-page: https://github.com/discoverySimulator/discoverySimulatorPythonPackage
Author: Leo Planquette & Eloise Lefebvre
Author-email: discoverysimulator@gmail.com
License: GPL v3
Keywords: robot robotic python students simulator education teaching
Platform: UNKNOWN
License-File: LICENSE
Requires-Dist: PyQt5
